ss_utils_safe_python/__init__.py
ss_utils_safe_python/snake_case.py
ss_utils_safe_python-0.0.1.dist-info/METADATA
ss_utils_safe_python-0.0.1.dist-info/WHEEL
ss_utils_safe_python-0.0.1.dist-info/licenses/LICENSE
ss_utils_safe_python-0.0.1.dist-info/RECORD
