Metadata-Version: 2.4
Name: ss-utils-safe-python
Version: 0.0.1
Summary: Utilities for logging with orjson serialization and advanced features
Project-URL: Homepage, https://github.com/shern2/ss-utils-safe-python
Project-URL: Repository, https://github.com/shern2/ss-utils-safe-python
Project-URL: Issues, https://github.com/shern2/ss-utils-safe-python/issues
Author: shern
License: MIT
License-File: LICENSE
Keywords: python,snake_case
Requires-Python: >=3.10
